{
  "Add": {
    "en": {
      "amount": {
        "volume": {
          "any": "{volume}",
          "else": "{mass}"
        }
      },
      "through_prefix": {
        "through": {
          "any": "through",
          "else": "directly"
        }
      },
      "time_prefix": {
        "time": {
          "any": "over",
          "else": "at default speed"
        }
      },
      "stir": {
        "stir": {
          "true": "with stirring",
          "false": "without stirring"
        }
      },
      "stir_speed": {
        "stir": {
          "true": "at {stir_speed}",
          "false": ""
        }
      },
      "full": "Add {reagent} ({amount}) {through_prefix} {through} to {vessel} {time_prefix} {time} {stir} {stir_speed}"
    },
    "zh": "\u52a0\u5165 {reagent}({volume}) \u81f3{vessel}.",
    "ru": "\u0414\u043e\u0431\u0430\u0432\u0438\u0442\u044c {reagent} ({volume}) \u0432 {vessel}."
  }
}
